hashicorp_vault/__init__.py
hashicorp_vault/authenticate_vault.py
hashicorp_vault/config_loader.py
hashicorp_vault/vault.py
hashicorp_vault_django-0.0.8.post1.dist-info/METADATA
hashicorp_vault_django-0.0.8.post1.dist-info/WHEEL
hashicorp_vault_django-0.0.8.post1.dist-info/top_level.txt
hashicorp_vault_django-0.0.8.post1.dist-info/RECORD
