Metadata-Version: 2.4
Name: hashicorp_vault_django
Version: 0.0.8.post1
Summary: A Django app to manage the application secrets using hashicorp.
Home-page: https://github.com/icedreamer-praveen/hashicorp-vault
Author: icedreamer-praveen
Author-email: prabinchy1234@gmail.com
License: MIT License
Keywords: vault,vault-django,hashicorp,hashicorp-vault-django,hashicorp_vault_django,hashicorp-vault,vault-secrets,vault-django,secrets-management,hashicorp-vault-integration,vault-configuration,vault-authentication,vault-python-client,vault-credentials,django-secrets,django-vault,django-config,django-auth,django-app,django-integration,django-security,django-secrets-management,django-settings,django-configuration,python-secrets,python-vault,python-authentication,python-security,python-secrets-ma
Classifier: Environment :: Web Environment
Classifier: Framework :: Django
Classifier: Intended Audience :: Developers
Classifier: License :: OSI Approved :: MIT License
Classifier: Operating System :: OS Independent
Classifier: Programming Language :: Python
Classifier: Programming Language :: Python :: 3.10
Classifier: Topic :: Internet :: WWW/HTTP
Classifier: Topic :: Internet :: WWW/HTTP :: Dynamic Content
Requires-Python: >=3.10
Requires-Dist: django>=3.2
Requires-Dist: hvac>=0.11.2
Provides-Extra: dev
Requires-Dist: twine>=4.0.2; extra == "dev"
Dynamic: author
Dynamic: author-email
Dynamic: classifier
Dynamic: description
Dynamic: description-content-type
Dynamic: home-page
Dynamic: keywords
Dynamic: license
Dynamic: provides-extra
Dynamic: requires-dist
Dynamic: requires-python
Dynamic: summary
